akoya/__init__.py
akoya-0.0.1.dist-info/licenses/LICENSE
akoya-0.0.1.dist-info/METADATA
akoya-0.0.1.dist-info/WHEEL
akoya-0.0.1.dist-info/top_level.txt
akoya-0.0.1.dist-info/RECORD
