Metadata-Version: 2.4
Name: akoya
Version: 0.0.1
Summary: akoya
License: The MIT License
Requires-Python: >=3.7
License-File: LICENSE
Dynamic: license-file
